flask_socketio/__init__.py
flask_socketio/namespace.py
flask_socketio/test_client.py
galileo_Flask_SocketIO-4.2.2.dev0.dist-info/LICENSE
galileo_Flask_SocketIO-4.2.2.dev0.dist-info/METADATA
galileo_Flask_SocketIO-4.2.2.dev0.dist-info/WHEEL
galileo_Flask_SocketIO-4.2.2.dev0.dist-info/top_level.txt
galileo_Flask_SocketIO-4.2.2.dev0.dist-info/RECORD
